wda_python/__init__.py
wda_python/_proto.py
wda_python/exceptions.py
wda_python/requests_usbmux.py
wda_python/usbmux.py
wda_python/utils.py
wda_python/xcui_element_types.py
wda_python-0.0.3.dist-info/AUTHORS
wda_python-0.0.3.dist-info/LICENSE
wda_python-0.0.3.dist-info/METADATA
wda_python-0.0.3.dist-info/WHEEL
wda_python-0.0.3.dist-info/pbr.json
wda_python-0.0.3.dist-info/top_level.txt
wda_python-0.0.3.dist-info/RECORD
